{
  "MODTRAN": [
    {
      "MODTRANINPUT": {
        "NAME": "blackbody_template_TPTEMP-300",
        "DESCRIPTION": "",
        "CASE": 0,
        "RTOPTIONS": {
          "MODTRN": "RT_CORRK_FAST",
          "LYMOLC": false,
          "T_BEST": false,
          "IEMSCT": "RT_SOLAR_AND_THERMAL",
          "IMULT": "RT_DISORT_AT_OBS",
          "DISALB": true,
          "NSTR": 8,
          "SOLCON": 0.0
        },
        "ATMOSPHERE": {
          "M1": "ATM_MIDLAT_SUMMER",
          "M2": "ATM_MIDLAT_SUMMER",
          "M3": "ATM_MIDLAT_SUMMER",
          "M4": "ATM_MIDLAT_SUMMER",
          "M5": "ATM_MIDLAT_SUMMER",
          "M6": "ATM_MIDLAT_SUMMER",
          "CO2MX": 420.0,
          "C_PROF": 3,
          "S_UMIX": [
            1.0,
            1.0,
            1.06,
            1.0,
            1.0,
            1.0,
            1.0,
            1.0,
            1.0,
            1.0
          ],
          "S_XSEC": [
            1.674,
            2.17,
            1.0,
            1.0,
            1.0,
            3.758,
            1.0,
            1.0,
            1.0,
            1.0,
            1.0,
            0.629,
            1.0
          ]
        },
        "AEROSOLS": {
          "IHAZE": "AER_RURAL",
          "ISEASN": "SEASN_SPRING_SUMMER",
          "VIS": 23.0
        },
        "GEOMETRY": {
          "ITYPE": 3,
          "H1ALT": 21.0,
          "IDAY": 121,
          "IPARM": 2,
          "PARM2": 20.0
        },
        "SURFACE": {
          "SURFTYPE": "REFL_CONSTANT",
          "TPTEMP": 300,
          "GNDALT": 0.315,
          "NSURF": 1,
          "SALBFL": ""
        },
        "SPECTRAL": {
          "V1": 600.0,
          "V2": 25000.0,
          "DV": 1.0,
          "FWHM": 1.0,
          "YFLAG": "R",
          "FLAGS": "WGA   T",
          "MLFLX": 4,
          "LBMNAM": "T",
          "BMNAME": "p1_2013"
        },
        "FILEOPTIONS": {
          "SLIPRNT": "blackbody_template_TPTEMP-300.sli",
          "CSVPRNT": "blackbody_template_TPTEMP-300.csv"
        }
      }
    },
    {
      "MODTRANINPUT": {
        "NAME": "blackbody_template_TPTEMP-350",
        "DESCRIPTION": "",
        "CASE": 0,
        "RTOPTIONS": {
          "MODTRN": "RT_CORRK_FAST",
          "LYMOLC": false,
          "T_BEST": false,
          "IEMSCT": "RT_SOLAR_AND_THERMAL",
          "IMULT": "RT_DISORT_AT_OBS",
          "DISALB": true,
          "NSTR": 8,
          "SOLCON": 0.0
        },
        "ATMOSPHERE": {
          "M1": "ATM_MIDLAT_SUMMER",
          "M2": "ATM_MIDLAT_SUMMER",
          "M3": "ATM_MIDLAT_SUMMER",
          "M4": "ATM_MIDLAT_SUMMER",
          "M5": "ATM_MIDLAT_SUMMER",
          "M6": "ATM_MIDLAT_SUMMER",
          "CO2MX": 420.0,
          "C_PROF": 3,
          "S_UMIX": [
            1.0,
            1.0,
            1.06,
            1.0,
            1.0,
            1.0,
            1.0,
            1.0,
            1.0,
            1.0
          ],
          "S_XSEC": [
            1.674,
            2.17,
            1.0,
            1.0,
            1.0,
            3.758,
            1.0,
            1.0,
            1.0,
            1.0,
            1.0,
            0.629,
            1.0
          ]
        },
        "AEROSOLS": {
          "IHAZE": "AER_RURAL",
          "ISEASN": "SEASN_SPRING_SUMMER",
          "VIS": 23.0
        },
        "GEOMETRY": {
          "ITYPE": 3,
          "H1ALT": 21.0,
          "IDAY": 121,
          "IPARM": 2,
          "PARM2": 20.0
        },
        "SURFACE": {
          "SURFTYPE": "REFL_CONSTANT",
          "TPTEMP": 350,
          "GNDALT": 0.315,
          "NSURF": 1,
          "SALBFL": ""
        },
        "SPECTRAL": {
          "V1": 600.0,
          "V2": 25000.0,
          "DV": 1.0,
          "FWHM": 1.0,
          "YFLAG": "R",
          "FLAGS": "WGA   T",
          "MLFLX": 4,
          "LBMNAM": "T",
          "BMNAME": "p1_2013"
        },
        "FILEOPTIONS": {
          "SLIPRNT": "blackbody_template_TPTEMP-350.sli",
          "CSVPRNT": "blackbody_template_TPTEMP-350.csv"
        }
      }
    },
    {
      "MODTRANINPUT": {
        "NAME": "blackbody_template_TPTEMP-400",
        "DESCRIPTION": "",
        "CASE": 0,
        "RTOPTIONS": {
          "MODTRN": "RT_CORRK_FAST",
          "LYMOLC": false,
          "T_BEST": false,
          "IEMSCT": "RT_SOLAR_AND_THERMAL",
          "IMULT": "RT_DISORT_AT_OBS",
          "DISALB": true,
          "NSTR": 8,
          "SOLCON": 0.0
        },
        "ATMOSPHERE": {
          "M1": "ATM_MIDLAT_SUMMER",
          "M2": "ATM_MIDLAT_SUMMER",
          "M3": "ATM_MIDLAT_SUMMER",
          "M4": "ATM_MIDLAT_SUMMER",
          "M5": "ATM_MIDLAT_SUMMER",
          "M6": "ATM_MIDLAT_SUMMER",
          "CO2MX": 420.0,
          "C_PROF": 3,
          "S_UMIX": [
            1.0,
            1.0,
            1.06,
            1.0,
            1.0,
            1.0,
            1.0,
            1.0,
            1.0,
            1.0
          ],
          "S_XSEC": [
            1.674,
            2.17,
            1.0,
            1.0,
            1.0,
            3.758,
            1.0,
            1.0,
            1.0,
            1.0,
            1.0,
            0.629,
            1.0
          ]
        },
        "AEROSOLS": {
          "IHAZE": "AER_RURAL",
          "ISEASN": "SEASN_SPRING_SUMMER",
          "VIS": 23.0
        },
        "GEOMETRY": {
          "ITYPE": 3,
          "H1ALT": 21.0,
          "IDAY": 121,
          "IPARM": 2,
          "PARM2": 20.0
        },
        "SURFACE": {
          "SURFTYPE": "REFL_CONSTANT",
          "TPTEMP": 400,
          "GNDALT": 0.315,
          "NSURF": 1,
          "SALBFL": ""
        },
        "SPECTRAL": {
          "V1": 600.0,
          "V2": 25000.0,
          "DV": 1.0,
          "FWHM": 1.0,
          "YFLAG": "R",
          "FLAGS": "WGA   T",
          "MLFLX": 4,
          "LBMNAM": "T",
          "BMNAME": "p1_2013"
        },
        "FILEOPTIONS": {
          "SLIPRNT": "blackbody_template_TPTEMP-400.sli",
          "CSVPRNT": "blackbody_template_TPTEMP-400.csv"
        }
      }
    },
    {
      "MODTRANINPUT": {
        "NAME": "blackbody_template_TPTEMP-450",
        "DESCRIPTION": "",
        "CASE": 0,
        "RTOPTIONS": {
          "MODTRN": "RT_CORRK_FAST",
          "LYMOLC": false,
          "T_BEST": false,
          "IEMSCT": "RT_SOLAR_AND_THERMAL",
          "IMULT": "RT_DISORT_AT_OBS",
          "DISALB": true,
          "NSTR": 8,
          "SOLCON": 0.0
        },
        "ATMOSPHERE": {
          "M1": "ATM_MIDLAT_SUMMER",
          "M2": "ATM_MIDLAT_SUMMER",
          "M3": "ATM_MIDLAT_SUMMER",
          "M4": "ATM_MIDLAT_SUMMER",
          "M5": "ATM_MIDLAT_SUMMER",
          "M6": "ATM_MIDLAT_SUMMER",
          "CO2MX": 420.0,
          "C_PROF": 3,
          "S_UMIX": [
            1.0,
            1.0,
            1.06,
            1.0,
            1.0,
            1.0,
            1.0,
            1.0,
            1.0,
            1.0
          ],
          "S_XSEC": [
            1.674,
            2.17,
            1.0,
            1.0,
            1.0,
            3.758,
            1.0,
            1.0,
            1.0,
            1.0,
            1.0,
            0.629,
            1.0
          ]
        },
        "AEROSOLS": {
          "IHAZE": "AER_RURAL",
          "ISEASN": "SEASN_SPRING_SUMMER",
          "VIS": 23.0
        },
        "GEOMETRY": {
          "ITYPE": 3,
          "H1ALT": 21.0,
          "IDAY": 121,
          "IPARM": 2,
          "PARM2": 20.0
        },
        "SURFACE": {
          "SURFTYPE": "REFL_CONSTANT",
          "TPTEMP": 450,
          "GNDALT": 0.315,
          "NSURF": 1,
          "SALBFL": ""
        },
        "SPECTRAL": {
          "V1": 600.0,
          "V2": 25000.0,
          "DV": 1.0,
          "FWHM": 1.0,
          "YFLAG": "R",
          "FLAGS": "WGA   T",
          "MLFLX": 4,
          "LBMNAM": "T",
          "BMNAME": "p1_2013"
        },
        "FILEOPTIONS": {
          "SLIPRNT": "blackbody_template_TPTEMP-450.sli",
          "CSVPRNT": "blackbody_template_TPTEMP-450.csv"
        }
      }
    }
  ]
}